biterm/__init__.py
biterm/__main__.py
biterm/btm.py
biterm/cbtm.cpython-36m-darwin.so
biterm/utility.py
biterm-0.1.5.dist-info/LICENSE
biterm-0.1.5.dist-info/METADATA
biterm-0.1.5.dist-info/WHEEL
biterm-0.1.5.dist-info/top_level.txt
biterm-0.1.5.dist-info/RECORD
