Metadata-Version: 2.1
Name: biterm
Version: 0.1.5
Summary: Biterm Topic Model
Home-page: https://github.com/markoarnauto/biterm
Author: markoarnauto
Author-email: markus.tretzmueller@cortecs.at
License: UNKNOWN
Platform: UNKNOWN
Classifier: Programming Language :: Python :: 3
Classifier: License :: OSI Approved :: MIT License
Classifier: Operating System :: OS Independent
Requires-Dist: numpy
Requires-Dist: tqdm
Requires-Dist: cython
Requires-Dist: nltk
